Metadata-Version: 2.1
Name: django-ueditor
Version: 1.0.2
Summary: Qitian Inc. Django UEditor plugins. For quick use in Django Admin Panel
Home-page: https://www.qitian.biz/
Author: Peter Han
Author-email: peter@qitian.com
License: MIT License
Keywords: django wysiwyg editor widget ueditor
Platform: UNKNOWN
Classifier: Development Status :: 5 - Production/Stable
Classifier: Environment :: Web Environment
Classifier: Framework :: Django
Classifier: Framework :: Django :: 1.11
Classifier: Framework :: Django :: 2.0
Classifier: Intended Audience :: Developers
Classifier: License :: OSI Approved :: MIT License
Classifier: Operating System :: OS Independent
Classifier: Programming Language :: Python
Classifier: Programming Language :: Python :: 3.5
Classifier: Programming Language :: Python :: 3.6
Classifier: Programming Language :: Python :: Implementation :: CPython
Classifier: Programming Language :: Python :: Implementation :: PyPy
Classifier: Topic :: Utilities
Requires-Python: >=3.6, !=3.0.*
